[
  {
    "order": 1,
    "image": "assets/img/dorlands_illustrated.jpg",
    "url": "https://opac.president.ac.id/index.php?p=show_detail&id=22998&keywords=Dorland%E2%80%99s+Illustrated+Medical+Dictionary"
  },
  {
    "order": 2,
    "image": "assets/img/sobbota_general.jpg",
    "url": "https://opac.president.ac.id/index.php?p=show_detail&id=22978&keywords=Sobotta%3A+General+Anatomy+and+Musculoskeletal+System"
  },
  {
    "order": 3,
    "image": "assets/img/sobotta_head.jpg",
    "url": "https://opac.president.ac.id/index.php?p=show_detail&id=22980&keywords=Sobotta%3A+Head%2C+Neck+and+Neuroanatomy"
  },
  {
    "order": 4,
    "image": "assets/img/anatomy_and.jpg",
    "url": "https://opac.president.ac.id/index.php?p=show_detail&id=23843&keywords=Anatomy+and+Physiology+Coloring+Workbook"
  },
  {
    "order": 5,
    "image": "assets/img/netters_atlas.jpg",
    "url": "https://opac.president.ac.id/index.php?p=show_detail&id=22995&keywords=Netter%E2%80%99s+Atlas+of+Human+Anatomy"
  },
  {
    "order": 6,
    "image": "assets/img/principles_of.jpg",
    "url": "https://opac.president.ac.id/index.php?p=show_detail&id=22990&keywords=Principles+of+Anatomy+and+Physiology%3A+Study+Guide"
  },
  {
    "order": 7,
    "image": "assets/img/bates_guide.jpg",
    "url": "https://opac.president.ac.id/index.php?p=show_detail&id=22992&keywords=Lynn+S.+Bickley"
  },
  {
    "order": 8,
    "image": "assets/img/sobotta_internal.jpg",
    "url": "https://opac.president.ac.id/index.php?p=show_detail&id=22979&keywords=Sobotta+atlas+of+anatomy%3A+Inner+Organs"
  },
  {
    "order": 9,
    "image": "assets/img/global_atlas.jpg",
    "url": "https://opac.president.ac.id/index.php?p=show_detail&id=23731&keywords=Global+Atlas+of+Allergy"
  },
  {
    "order": 10,
    "image": "assets/img/oxford_handbook.jpg",
    "url": "https://opac.president.ac.id/index.php?p=show_detail&id=22982&keywords=Oxford+Handbook+of+Clinical+Medicine"
  } 
]
