[
  {
    "order": 1,
    "image": "assets/img/Visual_Storytelling.png",
    "url": "https://opac.president.ac.id/index.php?p=show_detail&id=19125&keywords=Visual+Storytelling"
  },
  {
    "order": 2,
    "image": "assets/img/Unity.png",
    "url": "https://opac.president.ac.id/index.php?p=show_detail&id=20713&keywords=Unity%3A+Tutorial+Game+Engine"
  },
  {
    "order": 3,
    "image": "assets/img/Ultimate_logos.png",
    "url": "https://opac.president.ac.id/index.php?p=show_detail&id=18785&keywords=ultimate"
  },
  {
    "order": 4,
    "image": "assets/img/The_visual.png",
    "url": "https://opac.president.ac.id/index.php?p=show_detail&id=19162&keywords=The+visual"
  },
  {
    "order": 5,
    "image": "assets/img/The_best_of_newspaper.png",
    "url": "https://opac.president.ac.id/index.php?p=show_detail&id=18829&keywords=The+Best+of+Newspaper+Design"
  },
  {
    "order": 6,
    "image": "assets/img/Talk_to_me.png",
    "url": "https://opac.president.ac.id/index.php?p=show_detail&id=20960&keywords=talk"
  },
  {
    "order": 7,
    "image": "assets/img/Stamping_and_Printing.png",
    "url": "https://opac.president.ac.id/index.php?p=show_detail&id=21188&keywords=Stamping+and"
  },
  {
    "order": 8,
    "image": "assets/img/Rhythm_and_Verses.png",
    "url": "https://opac.president.ac.id/index.php?p=show_detail&id=19625&keywords=Rhythm"
  },
  {
    "order": 9,
    "image": "assets/img/9_Perspective.png",
    "url": "https://opac.president.ac.id/index.php?p=show_detail&id=16060&keywords=Perspective+An+essential"
  },
  {
    "order": 10,
    "image": "assets/img/Masterclass_Graphic.png",
    "url": "https://opac.president.ac.id/index.php?p=show_detail&id=19112&keywords=Masterclass+Graphic+Design"
  } 
]
